thetrove_downloader.py
thetrove_downloader-1.1.0.dist-info/entry_points.txt
thetrove_downloader-1.1.0.dist-info/LICENSE
thetrove_downloader-1.1.0.dist-info/WHEEL
thetrove_downloader-1.1.0.dist-info/METADATA
thetrove_downloader-1.1.0.dist-info/RECORD
