Metadata-Version: 2.1
Name: thetrove-downloader
Version: 1.1.0
Summary: Download utility for thetrove.is
Home-page: https://gitlab.com/MatteoCampinoti94/thetrove-downloader
License: EUPL-1.2
Author: Matteo Campinoti
Author-email: matteo.campinoti94@gmail.com
Requires-Python: >=3.9,<4.0
Classifier: Development Status :: 5 - Production/Stable
Classifier: Intended Audience :: End Users/Desktop
Classifier: License :: OSI Approved :: European Union Public Licence 1.2 (EUPL 1.2)
Classifier: Operating System :: OS Independent
Classifier: Programming Language :: Python :: 3
Classifier: Programming Language :: Python :: 3.9
Classifier: Topic :: Internet :: WWW/HTTP :: Indexing/Search
Requires-Dist: beautifulsoup4 (>=4.9.3,<5.0.0)
Requires-Dist: lxml (>=4.5.2,<5.0.0)
Requires-Dist: requests (>=2.24.0,<3.0.0)
Requires-Dist: rich (>=9.6.1,<10.0.0)
Requires-Dist: urllib3 (>=1.25.10,<2.0.0)
Project-URL: Repository, https://gitlab.com/MatteoCampinoti94/thetrove-downloader
